comnamepy/__init__.py
comnamepy/__main__.py
comnamepy/get_comname.py
comnamepy-1.1.8.dist-info/METADATA
comnamepy-1.1.8.dist-info/WHEEL
comnamepy-1.1.8.dist-info/entry_points.txt
comnamepy-1.1.8.dist-info/top_level.txt
comnamepy-1.1.8.dist-info/RECORD
