Metadata-Version: 2.1
Name: comnamepy
Version: 1.1.8
Summary: Get the company name from the domain.
Home-page: https://github.com/heku777/comnamepy
Author: heku777
Author-email: chotips08@gmail.com
Maintainer: heku777
Maintainer-email: chotips08@gmail.com
License: MIT
Platform: UNKNOWN
Classifier: Programming Language :: Python :: 3.6
Classifier: Programming Language :: Python :: 3.7
Classifier: Programming Language :: Python :: 3.8
Classifier: License :: OSI Approved :: MIT License
Requires-Python: >=3.6
Requires-Dist: beautifulsoup4 (==4.9.3)
Requires-Dist: python-whois (==0.7.3)
Requires-Dist: requests (==2.25.1)
